Workbook
Name Inv_Mensal: Sheet2!$E$17
Name Periodo_Invest: Sheet2!$E$18
Name Rendimento_Carteira: Sheet2!$E$13
Name Salario: Sheet2!$E$12
Name Sugestão_Investimento: Sheet2!$E$14
Name Tax_RenMensal: Sheet2!$E$19

Sheet Sheet2
C11: CONFIGURAÇÕES INICIAIS
C12: Salário | E12: 4000
C13: Rendimento Carteira | E13: 0.006
C14: Sugestão de Investimento (30%) | E14: =E12*30% -> 1200
C16: INVESTIMENTO MENSAL
C17: Investimento Mensal | E17: 150
C18: Anos de Investimento | E18: 5
C19: Taxa de Rendimento Mensal | E19: 0.01079
C20: Patrimônio Acumulado | E20: =FV(E19,E18*12,E17*-1) -> 12566.537
C21: Dividendos Mensais | E21: =E20*E19 -> 135.59294
C23: SIMULAÇÃO PATRIMÔNIO X INVESTIMENTO
C24: Tempo de Investimento | D24: Patrimônio Acumulado | E24: Dividendo
C25: 2 Anos | D25: =FV($E$19,2*12,$E$17*-1) -> 4084.1441 | E25: =D25*$E$13 -> 24.504865
C26: 5 Anos | D26: =FV($E$19,5*12,$E$17*-1) -> 12566.537 | E26: =D26*$E$13 -> 75.399223
C27: 10 Anos | D27: =FV($E$19,10*12,$E$17*-1) -> 36492.632 | E27: =D27*$E$13 -> 218.95579
C28: 20 Anos | D28: =FV($E$19,20*12,$E$17*-1) -> 168779.76 | E28: =D28*$E$13 -> 1012.6786
C29: 30 Anos | D29: =FV($E$19,30*12,$E$17*-1) -> 648325.45 | E29: =D29*$E$13 -> 3889.9527
C30: Para períodos especificos, seleciona abaixo o tempo de investimento:
D31: =FV($E$19,$C$31*12,$E$17*-1) -> 0 | E31: =D31*$E$13 -> 0
C41: PERFIL DO USUÁRIO | E41: Agressivo
C42: VALOR MENSAL A SER INVESTIDO | E42: =Inv_Mensal -> 150
C44: TIPO DE FII | D44: Percentual Sugerido | E44: Valores
C45: PAPEL | D45: {=_xlfn.XLOOKUP($C45,Base_Validação!$F$2:$F$7,_xlfn.XLOOKUP(Sheet2!$E$41,Base_Validação!$G$1:$I$1,Base_Validação!$G$2:$I$7))} -> 0.5 | E45: =$E$42*D45 -> 75
C46: TIJOLO | D46: {=_xlfn.XLOOKUP($C46,Base_Validação!$F$2:$F$7,_xlfn.XLOOKUP(Sheet2!$E$41,Base_Validação!$G$1:$I$1,Base_Validação!$G$2:$I$7))} -> 0.1 | E46: =$E$42*D46 -> 15
C47: HÍBRIDO | D47: {=_xlfn.XLOOKUP($C47,Base_Validação!$F$2:$F$7,_xlfn.XLOOKUP(Sheet2!$E$41,Base_Validação!$G$1:$I$1,Base_Validação!$G$2:$I$7))} -> 0.05 | E47: =$E$42*D47 -> 7.5
C48: FOFs | D48: {=_xlfn.XLOOKUP($C48,Base_Validação!$F$2:$F$7,_xlfn.XLOOKUP(Sheet2!$E$41,Base_Validação!$G$1:$I$1,Base_Validação!$G$2:$I$7))} -> 0.05 | E48: =$E$42*D48 -> 7.5
C49: DESENVOLVIMENTO | D49: {=_xlfn.XLOOKUP($C49,Base_Validação!$F$2:$F$7,_xlfn.XLOOKUP(Sheet2!$E$41,Base_Validação!$G$1:$I$1,Base_Validação!$G$2:$I$7))} -> 0.2 | E49: =$E$42*D49 -> 30
C50: HOTELARIAS | D50: {=_xlfn.XLOOKUP($C50,Base_Validação!$F$2:$F$7,_xlfn.XLOOKUP(Sheet2!$E$41,Base_Validação!$G$1:$I$1,Base_Validação!$G$2:$I$7))} -> 0.1 | E50: =$E$42*D50 -> 15
C51: TOTAL | E51: =SUM(E45:E50) -> 150

Sheet Base_Validação
A1: Número de anos | C1: Perfil do usuario | G1: Conservador | H1: Moderado | I1: Agressivo
C2: Conservador | F2: PAPEL | G2: 0.3 | H2: 0.32 | I2: 0.5
A3: 1 | C3: Moderado | F3: TIJOLO | G3: 0.5 | H3: 0.4 | I3: 0.1
A4: 2 | C4: Agressivo | F4: HÍBRIDO | G4: 0.1 | H4: 0.08 | I4: 0.05
A5: 3 | C5: BASE PERFIL | F5: FOFs | G5: 0.1 | H5: 0.1 | I5: 0.05
A6: 4 | F6: DESENVOLVIMENTO | G6: 0 | H6: 0.1 | I6: 0.2
A7: 5 | F7: HOTELARIAS | G7: 0 | H7: 0.1 | I7: 0.1
A8: 6 | F8: BASE PARA XLOOKUP
A9: 7
A10: 8
A11: 9
A12: 10
A13: 11
A14: 12
A15: 13
A16: 14
A17: 15
A18: 16
A19: 17
A20: 18
... A52: 50
